_nnls.cpython-312-x86_64-linux-musl.so
pyspecdata-0.9.45.3.data/purelib/pyspecdata/__init__.py
pyspecdata-0.9.45.3.data/purelib/pyspecdata/axis_class.py
pyspecdata-0.9.45.3.data/purelib/pyspecdata/core.py
pyspecdata-0.9.45.3.data/purelib/pyspecdata/datadir.py
pyspecdata-0.9.45.3.data/purelib/pyspecdata/dict_utils.py
pyspecdata-0.9.45.3.data/purelib/pyspecdata/figlist.py
pyspecdata-0.9.45.3.data/purelib/pyspecdata/fl_dummy.py
pyspecdata-0.9.45.3.data/purelib/pyspecdata/fornotebook.py
pyspecdata-0.9.45.3.data/purelib/pyspecdata/general_functions.py
pyspecdata-0.9.45.3.data/purelib/pyspecdata/generate_fake_data.py
pyspecdata-0.9.45.3.data/purelib/pyspecdata/hdf_utils.py
pyspecdata-0.9.45.3.data/purelib/pyspecdata/ipy.py
pyspecdata-0.9.45.3.data/purelib/pyspecdata/latexscripts.py
pyspecdata-0.9.45.3.data/purelib/pyspecdata/lmfitdata.py
pyspecdata-0.9.45.3.data/purelib/pyspecdata/lmfitdataGUI.py
pyspecdata-0.9.45.3.data/purelib/pyspecdata/mpl_utils.py
pyspecdata-0.9.45.3.data/purelib/pyspecdata/ndshape.py
pyspecdata-0.9.45.3.data/purelib/pyspecdata/nnls.py
pyspecdata-0.9.45.3.data/purelib/pyspecdata/placeholder.py
pyspecdata-0.9.45.3.data/purelib/pyspecdata/rec_utils.py
pyspecdata-0.9.45.3.data/purelib/pyspecdata/units.py
pyspecdata-0.9.45.3.data/purelib/pyspecdata/version.py
pyspecdata-0.9.45.3.data/purelib/pyspecdata/axis_manipulation/__init__.py
pyspecdata-0.9.45.3.data/purelib/pyspecdata/axis_manipulation/inhomog_coords.py
pyspecdata-0.9.45.3.data/purelib/pyspecdata/axis_manipulation/register_axis.py
pyspecdata-0.9.45.3.data/purelib/pyspecdata/axis_manipulation/secsy.py
pyspecdata-0.9.45.3.data/purelib/pyspecdata/axis_manipulation/shear.py
pyspecdata-0.9.45.3.data/purelib/pyspecdata/file_saving/hdf_save_dict_to_group.py
pyspecdata-0.9.45.3.data/purelib/pyspecdata/fourier/__init__.py
pyspecdata-0.9.45.3.data/purelib/pyspecdata/fourier/_ft_conj.py
pyspecdata-0.9.45.3.data/purelib/pyspecdata/fourier/convolve.py
pyspecdata-0.9.45.3.dist-info/METADATA
pyspecdata-0.9.45.3.dist-info/WHEEL
pyspecdata-0.9.45.3.dist-info/entry_points.txt
pyspecdata-0.9.45.3.dist-info/RECORD
