Metadata-Version: 2.1
Name: pyspecdata
Version: 0.9.45.3
Summary: Object-Oriented, Multi-dimensional Spectroscopic Data Processing
Author-Email: John Franck <john.franck@outlook.com>
Requires-Dist: sympy
Requires-Dist: numpy>=1.26.5
Requires-Dist: numexpr>=2.10.0
Requires-Dist: tables>=3.10.1
Requires-Dist: scipy
Requires-Dist: h5py
Requires-Dist: matplotlib>=3.8.0
Requires-Dist: pillow
Requires-Dist: pint
Requires-Dist: lmfit>=1.1
